DadosAbertosBrasil/__init__.py
DadosAbertosBrasil/bacen/__init__.py
DadosAbertosBrasil/bacen/_cambio.py
DadosAbertosBrasil/bacen/_expectativas.py
DadosAbertosBrasil/bacen/_moedas.py
DadosAbertosBrasil/bacen/_serie.py
DadosAbertosBrasil/camara/__init__.py
DadosAbertosBrasil/camara/_blocos.py
DadosAbertosBrasil/camara/_deputados.py
DadosAbertosBrasil/camara/_eventos.py
DadosAbertosBrasil/camara/_frentes.py
DadosAbertosBrasil/camara/_legislaturas.py
DadosAbertosBrasil/camara/_orgaos.py
DadosAbertosBrasil/camara/_partidos.py
DadosAbertosBrasil/camara/_proposicoes.py
DadosAbertosBrasil/camara/_referencias.py
DadosAbertosBrasil/camara/_votacoes.py
DadosAbertosBrasil/favoritos/__init__.py
DadosAbertosBrasil/ibge/__init__.py
DadosAbertosBrasil/ibge/_cidades.py
DadosAbertosBrasil/ibge/_misc.py
DadosAbertosBrasil/ibge/_nomes.py
DadosAbertosBrasil/ibge/_sidra.py
DadosAbertosBrasil/ipea/__init__.py
DadosAbertosBrasil/ipea/_referencias.py
DadosAbertosBrasil/ipea/_serie.py
DadosAbertosBrasil/senado/__init__.py
DadosAbertosBrasil/senado/_blocos.py
DadosAbertosBrasil/senado/_legislaturas.py
DadosAbertosBrasil/senado/_orcamentos.py
DadosAbertosBrasil/senado/_partidos.py
DadosAbertosBrasil/senado/_senadores.py
DadosAbertosBrasil/senado/_usos_palavras.py
DadosAbertosBrasil/uf/__init__.py
DadosAbertosBrasil/uf/_governador.py
DadosAbertosBrasil/uf/_uf.py
DadosAbertosBrasil/utils/__init__.py
DadosAbertosBrasil/utils/endpoints.py
DadosAbertosBrasil/utils/errors.py
DadosAbertosBrasil/utils/get.py
DadosAbertosBrasil/utils/parse.py
DadosAbertosBrasil/utils/typing.py
dadosabertosbrasil-2.0.1.dist-info/licenses/LICENSE.txt
tests/__init__.py
tests/test_bacen.py
tests/test_camara.py
tests/test_favoritos.py
tests/test_ibge.py
tests/test_ipea.py
tests/test_senado.py
tests/test_uf.py
dadosabertosbrasil-2.0.1.dist-info/METADATA
dadosabertosbrasil-2.0.1.dist-info/WHEEL
dadosabertosbrasil-2.0.1.dist-info/top_level.txt
dadosabertosbrasil-2.0.1.dist-info/RECORD
