Metadata-Version: 2.4
Name: DadosAbertosBrasil
Version: 2.0.1
Summary: Pacote Python para acesso a dados abertos e APIs do governo brasileiro.
Home-page: https://github.com/GusFurtado/DadosAbertosBrasil
Download-URL: https://github.com/GusFurtado/DadosAbertosBrasil/archive/2.0.1.tar.gz
Author: Gustavo Furtado
Author-email: gustavofurtado2@gmail.com
License: MIT
Keywords: brasil,ibge,ipea,ipeadata,camara,deputados,senado,senadores,bacen,bcb,bancocentral,dadosabertos,dadosgovbr
Classifier: Development Status :: 3 - Alpha
Classifier: Intended Audience :: Financial and Insurance Industry
Classifier: Intended Audience :: Science/Research
Classifier: Topic :: Scientific/Engineering
Classifier: License :: OSI Approved :: MIT License
Classifier: Natural Language :: Portuguese (Brazilian)
Classifier: Programming Language :: Python :: 3
Classifier: Programming Language :: Python :: 3.10
Classifier: Programming Language :: Python :: 3.11
Classifier: Programming Language :: Python :: 3.12
License-File: LICENSE.txt
Requires-Dist: pandas
Requires-Dist: pydantic
Requires-Dist: requests
Dynamic: author
Dynamic: author-email
Dynamic: classifier
Dynamic: description
Dynamic: description-content-type
Dynamic: download-url
Dynamic: home-page
Dynamic: keywords
Dynamic: license
Dynamic: license-file
Dynamic: requires-dist
Dynamic: summary
